[
  {
    "page_number": 0,
    "bbox": [
      91.82,
      773.59,
      495.21,
      782.59
    ],
    "text": "Rainfall amount (mm): Light: 00-12.5, Light to moderate: 12.5-25, Moderate: 25-50, Fairly heavy rain: 50 -100,",
    "fonts": [
      "Calibri"
    ],
    "sizes": [
      9.0
    ]
  },
  {
    "page_number": 0,
    "bbox": [
      195.65,
      786.19,
      390.92,
      795.19
    ],
    "text": "Heavy rain: 100 \u2013 150, Very heavy rain: 150 or more.",
    "fonts": [
      "Calibri"
    ],
    "sizes": [
      6.960000038146973,
      9.0
    ]
  },
  {
    "page_number": 0,
    "bbox": [
      99.86,
      797.43,
      490.99,
      810.52
    ],
    "text": "\u0dc0\u0dbb\u0dca\u0dc2\u0dcf\u0db4\u0dad\u0db1\u0dba(\u0db8\u0dd2.\u0db8\u0dd3) : \u0dc3\u0dd2\u0dc4\u0dd2\u0db1\u0dca \u0dc0\u0dd0\u0dc3\u0dd2: 00-12.5, \u0dc3\u0dd2\u0dc4\u0dd2\u0db1\u0dca \u0dc4 \u0ddd \u0db8\u0daf \u0dc0\u0dd0\u0dc3\u0dd2: 12.5-25, \u0db8\u0daf \u0dc0\u0dd0\u0dc3\u0dd2: 25-50, \u0dad\u0dbb\u0db8\u0d9a\u0dca \u0dad\u0daf \u0dc0\u0dd0\u0dc3\u0dd2: 50 -100,",
    "fonts": [
      "Calibri",
      "Iskoola Pota",
      "Times New Roman"
    ],
    "sizes": [
      2.0399999618530273,
      8.039999961853027,
      9.0
    ]
  },
  {
    "page_number": 0,
    "bbox": [
      207.29,
      811.94,
      379.72,
      822.16
    ],
    "text": "\u0dad\u0daf \u0dc0\u0dd0\u0dc3\u0dd2:100 \u2013 150, \u0d89\u0dad\u0dcf \u0dad\u0daf \u0dc0\u0dd0\u0dc3\u0dd2: 150 \u0dc4 \u0ddd \u0d8a\u0da7 \u0dc0\u0dd0\u0da9\u0dd2",
    "fonts": [
      "Iskoola Pota",
      "Times New Roman"
    ],
    "sizes": [
      8.039999961853027,
      9.0
    ]
  },
  {
    "page_number": 0,
    "bbox": [
      155.9,
      207.52,
      431.14,
      223.77
    ],
    "text": "\u0d89\u0daf\u0dd2\u0dbb\u0dd2 \u0db4\u0dd0\u0dba 36 \u0dc3\u0db3\u0dc4\u0dcf \u0dc3\u0dcf\u0db8\u0dcf\u0db1\u0dca\u200d\u0dba\u0dba \u0d9a\u0dcf\u0dbd\u0d9c\u0dd4\u0dab \u0d85\u0db1\u0dca\u200d\u0dcf\u0dc0\u0dd0\u0d9a\u0dd2\u0dba",
    "fonts": [
      "Iskoola Pota",
      "Iskoola Pota,Bold"
    ],
    "sizes": [
      14.039999961853027
    ]
  },
  {
    "page_number": 0,
    "bbox": [
      36.0,
      224.11,
      428.11,
      253.86
    ],
    "text": "2024 \u0da2\u0dd4\u0db1\u0dd2 \u0db8\u0dc3 23 \u0daf\u0dd2\u0db1\u0dca\u200d \u0dc3\u0dc0\u0dc3 04.00 \u0da7 \u0db1\u0dd2\u0d9a\u0dd4\u0dad\u0dca \u0d9a\u0dbb\u0db1\u0dca\u200d \u0dbd\u0daf\u0dd2.",
    "fonts": [
      "Iskoola Pota",
      "Iskoola Pota,Bold"
    ],
    "sizes": [
      12.479999542236328,
      12.960000038146973
    ]
  },
  {
    "page_number": 0,
    "bbox": [
      36.0,
      254.01,
      550.54,
      328.54
    ],
    "text": "\u0db6\u0dc3\u0dca\u0db1\u0dcf\u0dc4\u0dd2\u0dbb \u0dc3 \u0dc3\u0db6\u0dbb\u0d9c\u0db8\u0dd4\u0dc0 \u0db4\u0dc5\u0dcf\u0dad\u0dca\u0dc0\u0dbd\u0dad\u0dca \u0db8 \u0db1\u0dd4\u0dc0\u0dbb, \u0db1\u0dd4\u0dc0\u0dbb\u0d91\u0dc5\u0dd2\u0dba, \u0d9c\u0dcf\u0dbd\u0dca\u0dbd \u0dc3 \u0db8\u0dcf\u0dad\u0dbb \u0daf\u0dd2\u0dc3\u0dca\u0dd2\u0d9a\u0dca\u0d9a\u0dc0\u0dbd\u0dad\u0dca \u0dc0\u0dd2\u0da7\u0dd2\u0db1\u0dca \u0dc0\u0dd2\u0da7 \u0dc0\u0dd0\u0dc3\u0dd2 \u0d87\u0dad\u0dd2\u0dc4\u0dda. \u0db6\u0dc3\u0dca\u0db1\u0dcf\u0dc4\u0dd2\u0dbb \u0dc3 \u0dc3\u0db6\u0dbb\u0d9c\u0db8\u0dd4\u0dc0 \u0db4\u0dc5\u0dcf\u0dad\u0dca\u0dc0\u0dbd\u0dad\u0dca, \u0db8 \u0db1\u0dd4\u0dc0\u0dbb \u0dc3 \u0db1\u0dd4\u0dc0\u0dbb\u0d91\u0dc5\u0dd2\u0dba \u0daf\u0dd2\u0dc3\u0dca\u0dd2\u0d9a\u0dca\u0d9a\u0dc0\u0dbd\u0dad\u0dca \u0d87\u0dad\u0dd0\u0db8\u0dca \u0dc3\u0dca\u0dae\u0dcf\u0db1\u0dc0\u0dbd \u0db8\u0dd2.\u0db8\u0dd3. 50 \u0da7 \u0dc0\u0dd0\u0da9\u0dd2 \u0dad\u0dbb\u0db8\u0d9a\u0dca \u0dad\u0daf \u0dc0\u0dd0\u0dc3\u0dd2 \u0d87\u0dad\u0dd2\u0dc0\u0dd2\u0dba \u0dd0\u0d9a. \u0dc0\u0dba\u0db9 \u0db4\u0dc5\u0dcf\u0dc4\u0dad\u0dca \u0dc3 \u0db8\u0dcf\u0dad\u0dc4\u0dbd\u0dca \u0daf\u0dd2\u0dc3\u0dca\u0dd2\u0d9a\u0dca\u0d9a\u0dc4\u0dda \u0dc0\u0dd0\u0dc3\u0dd2\u0dc0\u0dcf\u0dbb \u0d9a\u0dd2\u0dc4\u0dd2\u0db4\u0dba\u0d9a\u0dca \u0d87\u0dad\u0dd2\u0dc4\u0dda.",
    "fonts": [
      "Iskoola Pota",
      "Iskoola Pota,Bold",
      "Times New Roman",
      "Times New Roman,Bold"
    ],
    "sizes": [
      3.9600000381469727,
      12.0
    ]
  },
  {
    "page_number": 0,
    "bbox": [
      36.0,
      328.56,
      550.52,
      399.92
    ],
    "text": "\u0db8\u0db0\u0dca\u200d\u0dba\u0db8 \u0d9a\u0db3\u0dd4\u0d9a\u0dbb\u0dc4\u0dda \u0db6\u0da7\u0dc4\u0dd2\u0dbb \u0db6\u0dd1\u0dc0\u0dd4\u0db8\u0dca \u0db4\u0dca\u200d\u0dbb\u0dc4\u0dda\u0dc1\u0dc0\u0dbd\u0dad\u0dca, \u0d8b\u0dad\u0dd4\u0dbb\u0dd4, \u0d8b\u0dad\u0dd4\u0dbb\u0dd4-\u0db8\u0dd0\u0daf \u0dc3 \u0dc0\u0dba\u0db9 \u0db4\u0dc5\u0dcf\u0dad\u0dca\u0dc0\u0dbd\u0dad\u0dca \u0dd2\u0d9a\u0dd4\u0dab\u0dcf\u0db8\u0dbd\u0dba, \u0db8\u0dca\u0db6\u0db1\u0dca\u0dc4\u0dad\u0dcf\u0da7 \u0dc3 \u0dc4\u0db8\u0dcf\u0dab\u0dbb\u0dcf\u0d9c\u0dbd \u0daf\u0dd2\u0dc3\u0dca\u0dd2\u0d9a\u0dca\u0d9a\u0dc0\u0dbd\u0dad\u0dca \u0dc0\u0dd2\u0da7\u0dd2\u0db1\u0dca \u0dc0\u0dd2\u0da7 \u0db8\u0db1 \u0db4\u0dd0.\u0d9a\u0dd2.\u0db8\u0dd3. (40-50) \u0d9a \u0db4\u0db8\u0dab \u0dad\u0daf \u0dc3\u0dd4\u0dc5\u0d82 \u0d87\u0dad\u0dd2\u0dc0\u0dd2\u0dba \u0dd0\u0d9a.",
    "fonts": [
      "Calibri,Bold",
      "Iskoola Pota",
      "Iskoola Pota,Bold",
      "Times New Roman",
      "Times New Roman,Bold"
    ],
    "sizes": [
      3.9600000381469727,
      12.0,
      14.039999961853027
    ]
  },
  {
    "page_number": 0,
    "bbox": [
      140.54,
      402.92,
      446.07,
      416.96
    ],
    "text": "GENERAL WEATHER FORECAST FOR NEXT 36 HOURS",
    "fonts": [
      "Calibri,Bold"
    ],
    "sizes": [
      14.039999961853027
    ]
  },
  {
    "page_number": 0,
    "bbox": [
      194.09,
      419.93,
      393.84,
      432.89
    ],
    "text": "Issued at 04.00 p.m. on 23 June 2024",
    "fonts": [
      "Calibri,Bold"
    ],
    "sizes": [
      12.479999542236328,
      12.960000038146973
    ]
  },
  {
    "page_number": 0,
    "bbox": [
      36.0,
      435.79,
      550.23,
      520.99
    ],
    "text": "Showers will occur at times in Western and Sabaragamuwa provinces and in Kandy, Nuwara Eliya, Galle and Matara districts. Fairly heavy showers above 50mm are likely at some places in Western and Sabaragamuwa provinces and in Kandy and Nuwara Eliya districts. Several spells of showers will occur in North-western province and in Matale district.",
    "fonts": [
      "Calibri",
      "Calibri,Bold",
      "Iskoola Pota"
    ],
    "sizes": [
      12.0,
      12.960000038146973
    ]
  },
  {
    "page_number": 0,
    "bbox": [
      36.0,
      522.37,
      550.07,
      573.43
    ],
    "text": "Strong winds of about (40-50) kmph can be expected at times over the Western slopes of the central hills, Northern, North-central and North-western provinces and in Trincomalee, Hambantota and Monaragala districts.",
    "fonts": [
      "Calibri",
      "Calibri,Bold",
      "Iskoola Pota"
    ],
    "sizes": [
      4.559999942779541,
      12.0
    ]
  },
  {
    "page_number": 0,
    "bbox": [
      41.4,
      112.51,
      396.86,
      172.58
    ],
    "text": "\u0dc1\u0dca\u200d\u0dbb\u0dd3 \u0dbd\u0d82\u0d9a\u0dcf\u0dc0 \u0dc3\u0db3\u0dc4\u0dcf \u0dc3\u0dcf\u0db8\u0dcf\u0db1\u0dca\u200d\u0dba\u0dba \u0d9a\u0dcf\u0dbd\u0d9c\u0dd4\u0dab \u0d85\u0db1\u0dca\u200d\u0dcf\u0dc0\u0dd0\u0d9a\u0dd2\u0dba GENERAL WEATHER FORECAST FOR SRI LANKA \u0da2\u0dcf\u0dad\u0dd2\u0d9a \u0d9a\u0dcf\u0dbd\u0d9c\u0dd4\u0dab \u0dc0\u0dd2\u0daf\u0dba\u0dcf \u0db8\u0db0\u0dca\u200d\u0dba\u0dc3\u0dca\u0dae\u0dcf\u0db1\u0dc4\u0dda, \u0d85\u0db1\u0dcf\u0dc0\u0dd0\u0d9a\u0dd2 \u0d85\u0d82\u0dc1\u0dba \u0db8\u0d9c\u0dd2\u0db1\u0dca \u0db1\u0dd2\u0d9a\u0dd4\u0dad\u0dca \u0d9a\u0dbb\u0db1 \u0dbd\u0daf\u0dd2 Issued by Forecasting Division, National Meteorological Centre",
    "fonts": [
      "Calibri",
      "Calibri,Bold",
      "Iskoola Pota",
      "Iskoola Pota,Bold"
    ],
    "sizes": [
      6.960000038146973,
      12.0,
      12.960000038146973
    ]
  },
  {
    "page_number": 1,
    "bbox": [
      91.82,
      773.59,
      495.21,
      782.59
    ],
    "text": "Rainfall amount (mm): Light: 00-12.5, Light to moderate: 12.5-25, Moderate: 25-50, Fairly heavy rain: 50 -100,",
    "fonts": [
      "Calibri"
    ],
    "sizes": [
      9.0
    ]
  },
  {
    "page_number": 1,
    "bbox": [
      195.65,
      786.19,
      390.92,
      795.19
    ],
    "text": "Heavy rain: 100 \u2013 150, Very heavy rain: 150 or more.",
    "fonts": [
      "Calibri"
    ],
    "sizes": [
      6.960000038146973,
      9.0
    ]
  },
  {
    "page_number": 1,
    "bbox": [
      99.86,
      797.43,
      490.99,
      810.52
    ],
    "text": "\u0dc0\u0dbb\u0dca\u0dc2\u0dcf\u0db4\u0dad\u0db1\u0dba(\u0db8\u0dd2.\u0db8\u0dd3) : \u0dc3\u0dd2\u0dc4\u0dd2\u0db1\u0dca \u0dc0\u0dd0\u0dc3\u0dd2: 00-12.5, \u0dc3\u0dd2\u0dc4\u0dd2\u0db1\u0dca \u0dc4 \u0ddd \u0db8\u0daf \u0dc0\u0dd0\u0dc3\u0dd2: 12.5-25, \u0db8\u0daf \u0dc0\u0dd0\u0dc3\u0dd2: 25-50, \u0dad\u0dbb\u0db8\u0d9a\u0dca \u0dad\u0daf \u0dc0\u0dd0\u0dc3\u0dd2: 50 -100,",
    "fonts": [
      "Calibri",
      "Iskoola Pota",
      "Times New Roman"
    ],
    "sizes": [
      2.0399999618530273,
      8.039999961853027,
      9.0
    ]
  },
  {
    "page_number": 1,
    "bbox": [
      207.29,
      811.94,
      379.72,
      822.16
    ],
    "text": "\u0dad\u0daf \u0dc0\u0dd0\u0dc3\u0dd2:100 \u2013 150, \u0d89\u0dad\u0dcf \u0dad\u0daf \u0dc0\u0dd0\u0dc3\u0dd2: 150 \u0dc4 \u0ddd \u0d8a\u0da7 \u0dc0\u0dd0\u0da9\u0dd2",
    "fonts": [
      "Iskoola Pota",
      "Times New Roman"
    ],
    "sizes": [
      8.039999961853027,
      9.0
    ]
  },
  {
    "page_number": 1,
    "bbox": [
      86.78,
      154.72,
      379.84,
      164.68
    ],
    "text": "Weather Forecast for Main Cities Date : 24-Jun-2024",
    "fonts": [
      "Times New Roman,Bold"
    ],
    "sizes": [
      9.0
    ]
  },
  {
    "page_number": 1,
    "bbox": [
      42.12,
      172.39,
      448.63,
      211.96
    ],
    "text": "City Temperature (0C) Relative Humidity (%) Weather Max Min Max Min Anuradhapura 33 26 90 60 Mainly fair",
    "fonts": [
      "Arial,Bold",
      "Times New Roman",
      "Times New Roman,Bold"
    ],
    "sizes": [
      6.0,
      9.0
    ]
  },
  {
    "page_number": 1,
    "bbox": [
      42.12,
      215.19,
      423.52,
      238.96
    ],
    "text": "Batticaloa 36 27 80 50 Mainly fair Colombo 31 26 90 75 Several spells of showers",
    "fonts": [
      "Arial,Bold",
      "Times New Roman",
      "Times New Roman,Bold"
    ],
    "sizes": [
      9.0
    ]
  },
  {
    "page_number": 1,
    "bbox": [
      42.12,
      242.19,
      423.52,
      265.99
    ],
    "text": "Galle 29 26 90 75 Several spells of showers Jaffna 32 28 85 70 Mainly fair",
    "fonts": [
      "Arial,Bold",
      "Times New Roman",
      "Times New Roman,Bold"
    ],
    "sizes": [
      9.0
    ]
  },
  {
    "page_number": 1,
    "bbox": [
      42.12,
      269.23,
      393.76,
      292.99
    ],
    "text": "Kandy 28 24 90 75 Showers at times Nuwara-Eliya 19 16 95 85 Showers at times",
    "fonts": [
      "Arial,Bold",
      "Times New Roman",
      "Times New Roman,Bold"
    ],
    "sizes": [
      9.0
    ]
  },
  {
    "page_number": 1,
    "bbox": [
      42.12,
      296.23,
      393.76,
      319.99
    ],
    "text": "Ratnapura 30 24 95 80 Showers at times Trincomalee 35 27 80 50 Mainly fair",
    "fonts": [
      "Arial,Bold",
      "Times New Roman",
      "Times New Roman,Bold"
    ],
    "sizes": [
      9.0
    ]
  },
  {
    "page_number": 1,
    "bbox": [
      42.12,
      323.23,
      373.12,
      333.55
    ],
    "text": "Mannar 31 28 80 55 Mainly fair",
    "fonts": [
      "Arial,Bold",
      "Times New Roman",
      "Times New Roman,Bold"
    ],
    "sizes": [
      9.0
    ]
  },
  {
    "page_number": 1,
    "bbox": [
      42.12,
      336.18,
      376.22,
      360.45
    ],
    "text": "\u0db4\u0dca\u200d\u0dbb\u0db0\u0dcf\u0db1\u0dca\u200d \u0db1\u0dca\u200d\u0d9c\u0dbb \u0dc3\u0daf\u0dc4\u0dcf \u0d9a\u0dcf\u0dbd\u0d9c\u0dd4\u0dab \u0d85\u0db1\u0dca\u200d\u0dcf\u0dc0\u0dd0\u0d9a\u0dd2\u0dba \u0daf\u0dd2\u0db1\u0dca\u200d\u0dba : 2024-06-24",
    "fonts": [
      "Calibri",
      "Iskoola Pota,Bold",
      "Times New Roman"
    ],
    "sizes": [
      9.0,
      9.960000038146973
    ]
  },
  {
    "page_number": 1,
    "bbox": [
      42.12,
      365.87,
      450.65,
      405.55
    ],
    "text": "\u0db1\u0dca\u200d\u0d9c\u0dbb\u0dba \u0d8b\u0dc2\u0dca\u0dab\u0dad\u0dca\u0dc0\u0dba(\u0dc3\u0dc3. \u0d85\u0d82\u0dc1\u0d9a) \u0dc3\u0dcf\u0dc3\u0dda\u0d9a\u0dca\u0dc2 \u0d86\u0dbb\u0dca\u0daf\u0dca\u200d\u0dbb\u0dad\u0dcf\u0dc0\u0dba(%) \u0d9a\u0dcf\u0dbd\u0d9c\u0dd4\u0dab\u0dba \u0d8b\u0db4\u0dbb\u0dd2\u0db8 \u0d85\u0dc0\u0db8 \u0d8b\u0db4\u0dbb\u0dd2\u0db8 \u0d85\u0dc0\u0db8 \u0d85\u0db1\u0dd4\u0dbb\u0dcf\u0db0\u0dca\u200d\u0db4\u0dd4\u0dbb\u0dba 33 26 90 60 \u0db4\u0dca\u200d\u0dbb\u0db0\u0dca\u200d\u0dcf\u0db1 \u0dc0\u0dc1\u0dc4\u0dba\u0db1\u0dca \u0dc0\u0dd0\u0dc3\u0dd2 \u0dbb\u0dc4\u0dd2\u0dad",
    "fonts": [
      "Iskoola Pota",
      "Iskoola Pota,Bold",
      "Times New Roman,Bold"
    ],
    "sizes": [
      9.0
    ]
  },
  {
    "page_number": 1,
    "bbox": [
      42.12,
      408.79,
      424.48,
      432.55
    ],
    "text": "\u0db8\u0da9\u0d9a\u0dbd\u0db4\u0dd4\u0dc0 36 27 80 50 \u0db4\u0dca\u200d\u0dbb\u0db0\u0dca\u200d\u0dcf\u0db1 \u0dc0\u0dc1\u0dc4\u0dba\u0db1\u0dca \u0dc0\u0dd0\u0dc3\u0dd2 \u0dbb\u0dc4\u0dd2\u0dad \u0dc4\u0d9a\u0dcf\u0dc5\u0db9 31 26 90 75 \u0dc0\u0dd0\u0dc3\u0dd2 \u0dc0\u0dcf\u0dbb \u0d9a\u0dd2\u0dc4\u0dd2\u0db4\u0dba\u0d9a\u0dca",
    "fonts": [
      "Iskoola Pota",
      "Times New Roman,Bold"
    ],
    "sizes": [
      9.0
    ]
  },
  {
    "page_number": 1,
    "bbox": [
      42.12,
      435.81,
      424.48,
      459.57
    ],
    "text": "\u0d9c\u0dcf\u0dbd\u0dca\u0dbd 29 26 90 75 \u0dc0\u0dd0\u0dc3\u0dd2 \u0dc0\u0dcf\u0dbb \u0d9a\u0dd2\u0dc4\u0dd2\u0db4\u0dba\u0d9a\u0dca \u0dba\u0dcf\u0db4\u0db1\u0dba 32 28 85 70 \u0db4\u0dca\u200d\u0dbb\u0db0\u0dca\u200d\u0dcf\u0db1 \u0dc0\u0dc1\u0dc4\u0dba\u0db1\u0dca \u0dc0\u0dd0\u0dc3\u0dd2 \u0dbb\u0dc4\u0dd2\u0dad",
    "fonts": [
      "Iskoola Pota",
      "Times New Roman,Bold"
    ],
    "sizes": [
      9.0
    ]
  },
  {
    "page_number": 1,
    "bbox": [
      42.12,
      462.81,
      382.96,
      486.57
    ],
    "text": "\u0db8 \u0db1\u0dd4\u0dc0\u0dbb 28 24 90 75 \u0dc0\u0dd2\u0da7\u0dd2\u0db1\u0dca \u0dc0\u0dd2\u0da7 \u0dc0\u0dd0\u0dc3\u0dd2 \u0db1\u0dd4\u0dc0\u0dbb\u0d91\u0dc5\u0dd2\u0dba 19 16 95 85 \u0dc0\u0dd2\u0da7\u0dd2\u0db1\u0dca \u0dc0\u0dd2\u0da7 \u0dc0\u0dd0\u0dc3\u0dd2",
    "fonts": [
      "Iskoola Pota",
      "Times New Roman,Bold"
    ],
    "sizes": [
      9.0
    ]
  },
  {
    "page_number": 1,
    "bbox": [
      42.12,
      489.81,
      424.48,
      513.57
    ],
    "text": "\u0dbb\u0dad\u0dca\u0db1\u0db4\u0dd4\u0dbb\u0dba 30 24 95 80 \u0dc0\u0dd2\u0da7\u0dd2\u0db1\u0dca \u0dc0\u0dd2\u0da7 \u0dc0\u0dd0\u0dc3\u0dd2 \u0dd2\u0d9a\u0dd4\u0dab\u0dcf\u0db8\u0dbd\u0dba 35 27 80 50 \u0db4\u0dca\u200d\u0dbb\u0db0\u0dca\u200d\u0dcf\u0db1 \u0dc0\u0dc1\u0dc4\u0dba\u0db1\u0dca \u0dc0\u0dd0\u0dc3\u0dd2 \u0dbb\u0dc4\u0dd2\u0dad",
    "fonts": [
      "Iskoola Pota",
      "Times New Roman,Bold"
    ],
    "sizes": [
      9.0
    ]
  },
  {
    "page_number": 1,
    "bbox": [
      42.12,
      516.81,
      424.48,
      527.03
    ],
    "text": "\u0db8\u0db1\u0dca\u0db1\u0dcf\u0dbb\u0db8 31 28 80 55 \u0db4\u0dca\u200d\u0dbb\u0db0\u0dca\u200d\u0dcf\u0db1 \u0dc0\u0dc1\u0dc4\u0dba\u0db1\u0dca \u0dc0\u0dd0\u0dc3\u0dd2 \u0dbb\u0dc4\u0dd2\u0dad",
    "fonts": [
      "Iskoola Pota",
      "Times New Roman,Bold"
    ],
    "sizes": [
      9.0
    ]
  },
  {
    "page_number": 1,
    "bbox": [
      70.58,
      542.19,
      241.29,
      552.56
    ],
    "text": "\u0baa\u0bbf\u0bb0\u0ba4\u0bbe\u0ba9 \u0ba8\u0b95\u0bb0\u0b99\u0bcd\u0b95\u0bb3\u0bc1\u0b95\u0bcd\u0b95\u0bbe\u0ba9 \u0bb5\u0bbe\u0ba9\u0bbf\u0bb2\u0bc8",
    "fonts": [
      "Leelawadee UI Semilight",
      "Nirmala UI,Bold"
    ],
    "sizes": [
      8.039999961853027
    ]
  },
  {
    "page_number": 1,
    "bbox": [
      117.26,
      547.47,
      369.4,
      563.29
    ],
    "text": "\u0bae\u0bc1\u0ba9\u0bcd\u0ba9\u0bb1\u0bbf\u0bb5\u0bbf\u0ba4\u0bcd\u0ba4\u0bc8\u0bcd \u0ba4\u0bbf\u0b95\u0ba4\u0bbf : 2024-06-24",
    "fonts": [
      "Leelawadee UI Semilight",
      "Nirmala UI,Bold",
      "Times New Roman,Bold"
    ],
    "sizes": [
      8.039999961853027
    ]
  },
  {
    "page_number": 1,
    "bbox": [
      67.34,
      572.43,
      99.71,
      582.85
    ],
    "text": "\u0ba8\u0b95\u0bb0\u0bae\u0bcd",
    "fonts": [
      "Nirmala UI,Bold",
      "Times New Roman,Bold"
    ],
    "sizes": [
      8.039999961853027
    ]
  },
  {
    "page_number": 1,
    "bbox": [
      138.74,
      565.71,
      303.74,
      576.13
    ],
    "text": "\u0bb5\u0bb5\u0baa\u0bcd\u0baa\u0ba8\u0bbf\u0bb2\u0bc8 (0C) \u0b9a\u0bbe\u0bb0\u0bc0\u0bb0\u0baa\u0bcd\u0baa\u0ba4\u0ba9\u0bcd (%)",
    "fonts": [
      "Leelawadee UI Semilight",
      "Nirmala UI,Bold",
      "Times New Roman,Bold"
    ],
    "sizes": [
      5.039999961853027,
      8.039999961853027
    ]
  },
  {
    "page_number": 1,
    "bbox": [
      139.22,
      572.43,
      454.87,
      589.57
    ],
    "text": "\u0bb5\u0bbe\u0ba9\u0bbf\u0bb2\u0bc8 \u0b89\u0b9a\u0bcd\u0b9a \u0b95\u0bc1\u0bb2\u0bc8\u0ba8\u0bcd\u0ba4 \u0b89\u0b9a\u0bcd\u0b9a \u0b95\u0bc1\u0bb2\u0bc8\u0ba8\u0bcd\u0ba4",
    "fonts": [
      "Nirmala UI,Bold",
      "Times New Roman,Bold"
    ],
    "sizes": [
      8.039999961853027
    ]
  },
  {
    "page_number": 1,
    "bbox": [
      42.12,
      592.71,
      446.32,
      603.08
    ],
    "text": "\u0b85\u0ba9\u0bc1\u0bb0\u0bbe\u0ba4\u0baa\u0bc1\u0bb0\u0bae\u0bcd 33 26 90 60 \u0baa\u0bbf\u0bb0\u0ba4\u0bbe\u0ba9\u0bae\u0bbe\u0b95 \u0b9a\u0bc0\u0bb0\u0bbe\u0ba9 \u0bb5\u0bbe\u0ba9\u0bbf\u0bb2\u0bc8",
    "fonts": [
      "Arial,Bold",
      "Leelawadee UI Semilight",
      "Nirmala UI",
      "Nirmala UI,Bold",
      "Times New Roman",
      "Times New Roman,Bold"
    ],
    "sizes": [
      6.960000038146973,
      8.039999961853027
    ]
  },
  {
    "page_number": 1,
    "bbox": [
      42.12,
      606.15,
      446.32,
      616.52
    ],
    "text": "\u0bae\u0b9f\u0bcd\u0b9f\u0b95\u0bcd\u0b95\u0bb3\u0baa\u0bcd\u0baa\u0bc1 36 27 80 50 \u0baa\u0bbf\u0bb0\u0ba4\u0bbe\u0ba9\u0bae\u0bbe\u0b95 \u0b9a\u0bc0\u0bb0\u0bbe\u0ba9 \u0bb5\u0bbe\u0ba9\u0bbf\u0bb2\u0bc8",
    "fonts": [
      "Arial,Bold",
      "Leelawadee UI Semilight",
      "Nirmala UI",
      "Nirmala UI,Bold",
      "Times New Roman",
      "Times New Roman,Bold"
    ],
    "sizes": [
      6.960000038146973,
      8.039999961853027
    ]
  },
  {
    "page_number": 1,
    "bbox": [
      42.12,
      619.74,
      426.37,
      630.11
    ],
    "text": "\u0bb5\u0b95\u0bbe\u0bb4\u0bc1\u0bae\u0bcd\u0baa\u0bc1 31 26 90 75 \u0b85\u0b9f\u0bbf\u0b95\u0bcd\u0b95\u0b9f\u0bbf \u0bae\u0bb2\u0bc8 \u0baa\u0bc6\u0baf\u0bcd\u0baf\u0bc1\u0bae\u0bcd",
    "fonts": [
      "Arial,Bold",
      "Leelawadee UI Semilight",
      "Nirmala UI",
      "Nirmala UI,Bold",
      "Times New Roman",
      "Times New Roman,Bold"
    ],
    "sizes": [
      6.960000038146973,
      8.039999961853027
    ]
  },
  {
    "page_number": 1,
    "bbox": [
      42.12,
      633.18,
      426.37,
      643.55
    ],
    "text": "\u0b95\u0bbe\u0bb2\u0bbf 29 26 90 75 \u0b85\u0b9f\u0bbf\u0b95\u0bcd\u0b95\u0b9f\u0bbf \u0bae\u0bb2\u0bc8 \u0baa\u0bc6\u0baf\u0bcd\u0baf\u0bc1\u0bae\u0bcd",
    "fonts": [
      "Arial,Bold",
      "Leelawadee UI Semilight",
      "Nirmala UI",
      "Nirmala UI,Bold",
      "Times New Roman",
      "Times New Roman,Bold"
    ],
    "sizes": [
      6.960000038146973,
      8.039999961853027
    ]
  },
  {
    "page_number": 1,
    "bbox": [
      42.12,
      646.74,
      446.32,
      657.11
    ],
    "text": "\u0baf\u0bbe\u0bb4\u0bcd\u0baa\u0bcd\u0baa\u0bbe\u0ba3\u0bae\u0bcd 32 28 85 70 \u0baa\u0bbf\u0bb0\u0ba4\u0bbe\u0ba9\u0bae\u0bbe\u0b95 \u0b9a\u0bc0\u0bb0\u0bbe\u0ba9 \u0bb5\u0bbe\u0ba9\u0bbf\u0bb2\u0bc8",
    "fonts": [
      "Arial,Bold",
      "Leelawadee UI Semilight",
      "Nirmala UI",
      "Nirmala UI,Bold",
      "Times New Roman",
      "Times New Roman,Bold"
    ],
    "sizes": [
      6.960000038146973,
      8.039999961853027
    ]
  },
  {
    "page_number": 1,
    "bbox": [
      42.12,
      660.18,
      442.12,
      670.55
    ],
    "text": "\u0b95\u0ba3\u0bcd\u0b9f\u0bbf 28 24 90 75 \u0b85\u0bb5\u0bcd\u0bb5\u0bc6\u0bcd\u0baa\u0bc6\u0bbe\u0ba4\u0bc1 \u0bae\u0bb2\u0bc8 \u0baa\u0bc6\u0baf\u0bcd\u0baf\u0bc1\u0bae\u0bcd",
    "fonts": [
      "Arial,Bold",
      "Leelawadee UI Semilight",
      "Nirmala UI",
      "Nirmala UI,Bold",
      "Times New Roman",
      "Times New Roman,Bold"
    ],
    "sizes": [
      6.960000038146973,
      8.039999961853027
    ]
  },
  {
    "page_number": 1,
    "bbox": [
      42.12,
      673.74,
      442.12,
      684.11
    ],
    "text": "\u0ba8\u0bc1\u0bb5\u0bb5\u0bb0\u0bb2\u0bbf\u0baf\u0bbe 19 16 95 85 \u0b85\u0bb5\u0bcd\u0bb5\u0bc6\u0bcd\u0baa\u0bc6\u0bbe\u0ba4\u0bc1 \u0bae\u0bb2\u0bc8 \u0baa\u0bc6\u0baf\u0bcd\u0baf\u0bc1\u0bae\u0bcd",
    "fonts": [
      "Arial,Bold",
      "Leelawadee UI Semilight",
      "Nirmala UI",
      "Nirmala UI,Bold",
      "Times New Roman",
      "Times New Roman,Bold"
    ],
    "sizes": [
      6.960000038146973,
      8.039999961853027
    ]
  },
  {
    "page_number": 1,
    "bbox": [
      42.12,
      687.18,
      442.12,
      697.55
    ],
    "text": "\u0b87\u0bb0\u0ba4\u0bcd\u0ba4\u0bbf\u0ba9\u0baa\u0bc1\u0bb0\u0bbf 30 24 95 80 \u0b85\u0bb5\u0bcd\u0bb5\u0bc6\u0bcd\u0baa\u0bc6\u0bbe\u0ba4\u0bc1 \u0bae\u0bb2\u0bc8 \u0baa\u0bc6\u0baf\u0bcd\u0baf\u0bc1\u0bae\u0bcd",
    "fonts": [
      "Arial,Bold",
      "Leelawadee UI Semilight",
      "Nirmala UI",
      "Nirmala UI,Bold",
      "Times New Roman",
      "Times New Roman,Bold"
    ],
    "sizes": [
      6.960000038146973,
      8.039999961853027
    ]
  },
  {
    "page_number": 1,
    "bbox": [
      42.12,
      700.74,
      446.32,
      711.11
    ],
    "text": "\u0ba4\u0bbf\u0bb0\u0bc1\u0b95\u0b95\u0bbe\u0ba3\u0bae\u0bb2\u0bc8 35 27 80 50 \u0baa\u0bbf\u0bb0\u0ba4\u0bbe\u0ba9\u0bae\u0bbe\u0b95 \u0b9a\u0bc0\u0bb0\u0bbe\u0ba9 \u0bb5\u0bbe\u0ba9\u0bbf\u0bb2\u0bc8",
    "fonts": [
      "Arial,Bold",
      "Leelawadee UI Semilight",
      "Nirmala UI",
      "Nirmala UI,Bold",
      "Times New Roman",
      "Times New Roman,Bold"
    ],
    "sizes": [
      6.960000038146973,
      8.039999961853027
    ]
  },
  {
    "page_number": 1,
    "bbox": [
      36.0,
      713.46,
      446.32,
      740.26
    ],
    "text": "\u0bae\u0ba9\u0bcd\u0ba9\u0bbe\u0bb0\u0bcd 31 28 80 55 \u0baa\u0bbf\u0bb0\u0ba4\u0bbe\u0ba9\u0bae\u0bbe\u0b95 \u0b9a\u0bc0\u0bb0\u0bbe\u0ba9 \u0bb5\u0bbe\u0ba9\u0bbf\u0bb2\u0bc8",
    "fonts": [
      "Arial,Bold",
      "Calibri,Bold",
      "Leelawadee UI Semilight",
      "Nirmala UI",
      "Nirmala UI,Bold",
      "Times New Roman",
      "Times New Roman,Bold"
    ],
    "sizes": [
      6.960000038146973,
      8.039999961853027,
      12.0
    ]
  }
]